nonebot_plugin_npu/SmileySans-Oblique.ttf
nonebot_plugin_npu/__init__.py
nonebot_plugin_npu/command.py
nonebot_plugin_npu/config.py
nonebot_plugin_npu/draw_course_schedule_pic.py
nonebot_plugin_npu/draw_empty_classroom_pic.py
nonebot_plugin_npu/jwxt/get_new_cookie_Fkjfy9yPdPQuP.py
nonebot_plugin_npu/jwxt/rs6.js
nonebot_plugin_npu/nwpu_electric.py
nonebot_plugin_npu/nwpu_query.py
nonebot_plugin_npu/schedule.py
nonebot_plugin_npu/utils.py
nonebot_plugin_npu-2.0.5.dist-info/METADATA
nonebot_plugin_npu-2.0.5.dist-info/WHEEL
nonebot_plugin_npu-2.0.5.dist-info/licenses/LICENSE
nonebot_plugin_npu-2.0.5.dist-info/RECORD
