Metadata-Version: 2.4
Name: nonebot-plugin-npu
Version: 2.0.5
Summary: 翱翔门户成绩监控插件，能获取成绩、排名、绩点，当出现新成绩时推送给使用者
License-File: LICENSE
Keywords: nonebot,nonebot2,npu,nwpu
Author: qllokirin
Requires-Python: >=3.9,<4.0
Classifier: Programming Language :: Python :: 3
Classifier: Programming Language :: Python :: 3.9
Classifier: Programming Language :: Python :: 3.10
Classifier: Programming Language :: Python :: 3.11
Classifier: Programming Language :: Python :: 3.12
Classifier: Programming Language :: Python :: 3.13
Classifier: Programming Language :: Python :: 3.14
Requires-Dist: beautifulsoup4 (>=4.12.3,<5.0.0)
Requires-Dist: httpx (>=0.27.2,<0.28.0)
Requires-Dist: imgkit (>=0.1.5,!=1.0.5)
Requires-Dist: nonebot-adapter-onebot (>=2.4.5,<3.0.0)
Requires-Dist: nonebot-plugin-apscheduler (>=0.5.0,<0.6.0)
Requires-Dist: nonebot-plugin-waiter (>=0.8.0,<0.9.0)
Requires-Dist: nonebot2 (>=2.3.3,<3.0.0)
Requires-Dist: openpyxl (>=3.1.5,<4.0.0)
Requires-Dist: pillow (>=10.0.0,<11.0.0)
Requires-Dist: rsa (>=4.9,<5.0)
